subfiles/__init__.py
subfiles/cli.py
subfiles/commands/__init__.py
subfiles/commands/base.py
subfiles/commands/hello.py
subfiles/commands/list.py
subfiles/commands/schema.py
subfiles/commands/utils.py
subfiles-1.0.8.dist-info/DESCRIPTION.rst
subfiles-1.0.8.dist-info/METADATA
subfiles-1.0.8.dist-info/RECORD
subfiles-1.0.8.dist-info/WHEEL
subfiles-1.0.8.dist-info/entry_points.txt
subfiles-1.0.8.dist-info/metadata.json
subfiles-1.0.8.dist-info/top_level.txt
